odoo/addons/stock_restrict_lot/README.rst
odoo/addons/stock_restrict_lot/__init__.py
odoo/addons/stock_restrict_lot/__manifest__.py
odoo/addons/stock_restrict_lot/i18n/it.po
odoo/addons/stock_restrict_lot/i18n/stock_restrict_lot.pot
odoo/addons/stock_restrict_lot/models/__init__.py
odoo/addons/stock_restrict_lot/models/product_product.py
odoo/addons/stock_restrict_lot/models/stock_move.py
odoo/addons/stock_restrict_lot/models/stock_rule.py
odoo/addons/stock_restrict_lot/readme/CONTRIBUTORS.rst
odoo/addons/stock_restrict_lot/readme/DESCRIPTION.rst
odoo/addons/stock_restrict_lot/static/description/icon.png
odoo/addons/stock_restrict_lot/static/description/index.html
odoo/addons/stock_restrict_lot/tests/__init__.py
odoo/addons/stock_restrict_lot/tests/test_restrict_lot.py
odoo14_addon_stock_restrict_lot-14.0.1.4.1.dist-info/METADATA
odoo14_addon_stock_restrict_lot-14.0.1.4.1.dist-info/WHEEL
odoo14_addon_stock_restrict_lot-14.0.1.4.1.dist-info/top_level.txt
odoo14_addon_stock_restrict_lot-14.0.1.4.1.dist-info/RECORD
